unplug/__init__.py
unplug/tui.py
unplug/data/at-keyboard-a-press.yml
unplug/data/at-keyboard-a-release.yml
unplug/data/at-keyboard-space.yml
unplug/data/wacom-intuos-pro-2-m-pad-btn_0-press.yml
unplug/data/wacom-intuos-pro-2-m-pad-btn_0-pressrelease.yml
unplug/data/wacom-intuos-pro-2-m-pad-btn_0-release.yml
unplug/data/wacom-intuos-pro-2-m-pad-mode-toggle.yml
unplug/data/wacom-intuos-pro-2-m-pad-ring-ccw.yml
unplug/data/wacom-intuos-pro-2-m-pad-ring-cw.yml
unplug/data/wacom-intuos-pro-2-m-pen-noevents.yml
unplug/data/wacom-intuos-pro-l-BTN_0-press.yml
unplug/data/wacom-intuos-pro-l-BTN_0-release.yml
unplug/data/wacom-intuos-pro-l-BTN_0.yml
unplug/data/wacom-intuos-pro-l-BTN_8.yml
unplug/data/wacom-intuos-pro-l-BTN_9.yml
unplug/data/wacom-intuos-pro-l-hwheel-neg-single.yml
unplug/data/wacom-intuos-pro-l-hwheel-pos-single.yml
unplug/data/wacom-intuos-pro-l-pen-noevents.yml
unplug/data/wacom-intuos-pro-l-wheel-neg-single.yml
unplug/data/wacom-intuos-pro-l-wheel-neg.yml
unplug/data/wacom-intuos-pro-l-wheel-pos-single.yml
unplug/data/wacom-intuos-pro-l-wheel-pos.yml
unplug/data/yubikey-noevents.yml
unplug-0.1.1.dist-info/METADATA
unplug-0.1.1.dist-info/WHEEL
unplug-0.1.1.dist-info/entry_points.txt
unplug-0.1.1.dist-info/licenses/LICENSE
unplug-0.1.1.dist-info/RECORD
