Metadata-Version: 2.4
Name: unplug
Version: 0.1.1
Summary: TUI that allows creating and replaying uinput devices from libinput recordings
Author-email: Peter Hutterer <peter.hutterer@who-t.net>
License-Expression: GPL-3.0-or-later
License-File: LICENSE
Requires-Python: >=3.13
Requires-Dist: libevdev>=0.12
Requires-Dist: pyyaml>=6.0.2
Requires-Dist: rich>=14.1.0
Requires-Dist: textual>=5.0.1
